abstractassistant/__init__.py
abstractassistant/app.py
abstractassistant/cli.py
abstractassistant/config.py
abstractassistant/create_app_bundle.py
abstractassistant/web_server.py
abstractassistant/core/__init__.py
abstractassistant/core/llm_manager.py
abstractassistant/core/tts_manager.py
abstractassistant/ui/__init__.py
abstractassistant/ui/chat_bubble.py
abstractassistant/ui/history_dialog.py
abstractassistant/ui/provider_manager.py
abstractassistant/ui/qt_bubble.py
abstractassistant/ui/toast_manager.py
abstractassistant/ui/toast_window.py
abstractassistant/ui/tts_state_manager.py
abstractassistant/ui/ui_styles.py
abstractassistant/utils/__init__.py
abstractassistant/utils/icon_generator.py
abstractassistant/utils/markdown_renderer.py
abstractassistant-0.3.5.dist-info/licenses/LICENSE
abstractassistant-0.3.5.dist-info/METADATA
abstractassistant-0.3.5.dist-info/WHEEL
abstractassistant-0.3.5.dist-info/entry_points.txt
abstractassistant-0.3.5.dist-info/top_level.txt
abstractassistant-0.3.5.dist-info/RECORD
