Metadata-Version: 2.4
Name: abstractassistant
Version: 0.3.5
Summary: A sleek (macOS) system tray application providing instant access to LLMs
Author-email: Laurent-Philippe Albou <contact@abstractcore.ai>
License-Expression: MIT
Project-URL: Homepage, https://github.com/lpalbou/abstractassistant
Project-URL: Repository, https://github.com/lpalbou/abstractassistant
Project-URL: Issues, https://github.com/lpalbou/abstractassistant/issues
Keywords: ai,llm,macos,system-tray,assistant
Classifier: Development Status :: 4 - Beta
Classifier: Intended Audience :: End Users/Desktop
Classifier: Operating System :: MacOS
Classifier: Programming Language :: Python :: 3
Classifier: Programming Language :: Python :: 3.9
Classifier: Programming Language :: Python :: 3.10
Classifier: Programming Language :: Python :: 3.11
Classifier: Programming Language :: Python :: 3.12
Classifier: Topic :: Scientific/Engineering :: Artificial Intelligence
Classifier: Topic :: Desktop Environment
Requires-Python: >=3.9
License-File: LICENSE
Requires-Dist: abstractcore[anthropic,lmstudio,ollama,openai,tools]>=2.9.1
Requires-Dist: pystray>=0.19.4
Requires-Dist: Pillow>=10.0.0
Requires-Dist: PyQt5>=5.15.0
Requires-Dist: markdown>=3.5.0
Requires-Dist: pygments>=2.16.0
Requires-Dist: pymdown-extensions>=10.0
Requires-Dist: abstractvoice>=0.5.2
Requires-Dist: pyperclip>=1.8.2
Requires-Dist: plyer>=2.1.0
Requires-Dist: tomli>=2.0.0; python_version < "3.11"
Requires-Dist: tomli-w>=1.0.0
Provides-Extra: dev
Requires-Dist: pytest>=7.0.0; extra == "dev"
Requires-Dist: black>=23.0.0; extra == "dev"
Requires-Dist: isort>=5.12.0; extra == "dev"
Requires-Dist: mypy>=1.5.0; extra == "dev"
Dynamic: license-file
